zappa_packer/__init__.py
zappa_packer/cli.py
zappa_packer/handler.py
zappa_packer/middleware.py
zappa_packer/utilities.py
zappa_packer/wsgi.py
zappa_packer/zappa.py
zappa_packer-0.0.5.dist-info/METADATA
zappa_packer-0.0.5.dist-info/WHEEL
zappa_packer-0.0.5.dist-info/entry_points.txt
zappa_packer-0.0.5.dist-info/top_level.txt
zappa_packer-0.0.5.dist-info/RECORD
